{"dossierParlementaire": {"@xmlns": "http://schemas.assemblee-nationale.fr/referentiel", "@xmlns:xsi": "http://www.w3.org/2001/XMLSchema-instance", "@xsi:type": "DossierMissionControle_Type", "uid": "DLR5L16N49118", "legislature": "16", "titreDossier": {"titre": "L'activit\u00e9 de la d\u00e9l\u00e9gation fran\u00e7aise \u00e0 l'Assembl\u00e9e parlementaire de l'OTAN au cours de l\u2019ann\u00e9e 2022", "titreChemin": "ap_otan_2022", "senatChemin": null}, "procedureParlementaire": {"code": "19", "libelle": "Rapport d'information sans mission"}, "initiateur": null, "actesLegislatifs": {"acteLegislatif": {"@xsi:type": "Etape_Type", "uid": "L16-AN20-49118", "codeActe": "AN20", "libelleActe": {"nomCanonique": "Travaux"}, "organeRef": "PO791932", "dateActe": null, "actesLegislatifs": {"acteLegislatif": {"@xsi:type": "DepotRapport_Type", "uid": "L16-VD217113", "codeActe": "AN20-RAPPORT", "libelleActe": {"nomCanonique": "D\u00e9p\u00f4t de rapport", "libelleCourt": "D\u00e9p\u00f4t de rapport"}, "organeRef": "PO58974", "dateActe": "2023-12-19T00:00:00.000+01:00", "actesLegislatifs": null, "texteAssocie": "RINFANR5L16B2011", "texteAdopte": null}}}}, "fusionDossier": null}}