{"dossierParlementaire": {"@xmlns": "http://schemas.assemblee-nationale.fr/referentiel", "@xmlns:xsi": "http://www.w3.org/2001/XMLSchema-instance", "@xsi:type": "DossierLegislatif_Type", "uid": "DLR5L16N46270", "legislature": "16", "titreDossier": {"titre": "Proposition de loi cr\u00e9ant une aide universelle d'urgence pour les victimes de violences conjugales", "titreChemin": "DLR5L16N46270", "senatChemin": "http://www.senat.fr/dossier-legislatif/ppl21-875.html"}, "procedureParlementaire": {"code": "2", "libelle": "Proposition de loi ordinaire"}, "initiateur": {"acteurs": {"acteur": {"acteurRef": "PA227089", "mandatRef": "PM736372"}}, "organes": {"organe": {"organeRef": {"uid": "PO78718"}}}}, "actesLegislatifs": {"acteLegislatif": [{"@xsi:type": "Etape_Type", "uid": "L16-SN1-46270", "codeActe": "SN1", "libelleActe": {"nomCanonique": "1\u00e8re lecture (1\u00e8re assembl\u00e9e saisie)", "libelleCourt": "1\u00e8re lecture"}, "organeRef": "PO78718", "dateActe": null, "actesLegislatifs": {"acteLegislatif": [{"@xsi:type": "DepotInitiative_Type", "uid": "L16-VD209018DI", "codeActe": "SN1-DEPOT", "libelleActe": {"nomCanonique": "1er d\u00e9p\u00f4t d'une initiative.", "libelleCourt": "1er d\u00e9p\u00f4t d'une initiative."}, "organeRef": "PO78718", "dateActe": "2022-09-06T00:00:00.000+02:00", "actesLegislatifs": null, "texteAssocie": "PIONSNR5S379B0875"}, {"@xsi:type": "Etape_Type", "uid": "L16-SN1-COM-46270", "codeActe": "SN1-COM", "libelleActe": {"nomCanonique": "Travaux des commissions", "libelleCourt": "Travaux des commissions"}, "organeRef": "PO78718", "dateActe": null, "actesLegislatifs": {"acteLegislatif": {"@xsi:type": "Etape_Type", "uid": "L16-VD209019CF", "codeActe": "SN1-COM-FOND", "libelleActe": {"nomCanonique": "Travaux de la commission saisie au fond", "libelleCourt": "Travaux de la commission saisie au fond"}, "organeRef": "PO211493", "dateActe": null, "actesLegislatifs": {"acteLegislatif": [{"@xsi:type": "SaisieComFond_Type", "uid": "L16-VD209019CFS", "codeActe": "SN1-COM-FOND-SAISIE", "libelleActe": {"nomCanonique": "Renvoi en commission au fond", "libelleCourt": "Renvoi en commission au fond"}, "organeRef": "PO211493", "dateActe": "2022-09-06T00:00:00.000+02:00", "actesLegislatifs": null}, {"@xsi:type": "NominRapporteurs_Type", "uid": "L16-VD209328", "codeActe": "SN1-COM-FOND-NOMIN", "libelleActe": {"nomCanonique": "Nomination de rapporteur", "libelleCourt": "Nomination de rapporteur"}, "organeRef": "PO211493", "dateActe": null, "actesLegislatifs": null, "rapporteurs": {"rapporteur": {"acteurRef": "PA736206", "typeRapporteur": "rapporteur"}}, "reunion": null}, {"@xsi:type": "DepotRapport_Type", "uid": "L16-VD209329", "codeActe": "SN1-COM-FOND-RAPPORT", "libelleActe": {"nomCanonique": "D\u00e9p\u00f4t de rapport", "libelleCourt": "D\u00e9p\u00f4t de rapport"}, "organeRef": "PO211493", "dateActe": "2022-10-05T00:00:00.000+02:00", "actesLegislatifs": null, "texteAssocie": "RAPPSNR5S399B0021", "texteAdopte": "PIONSNR5S399BTC0022"}]}}}}, {"@xsi:type": "Etape_Type", "uid": "L16-SN1-DEBATS-46270", "codeActe": "SN1-DEBATS", "libelleActe": {"nomCanonique": "Discussion en s\u00e9ance publique", "libelleCourt": "Discussion en s\u00e9ance publique"}, "organeRef": "PO78718", "dateActe": null, "actesLegislatifs": {"acteLegislatif": {"@xsi:type": "Decision_Type", "uid": "L16-VD209622DEC", "codeActe": "SN1-DEBATS-DEC", "libelleActe": {"nomCanonique": "D\u00e9cision", "libelleCourt": "D\u00e9cision"}, "organeRef": "PO78718", "dateActe": "2022-10-20T00:00:00.000+02:00", "actesLegislatifs": null, "statutConclusion": {"fam_code": "TSORTF01", "libelle": "adopt\u00e9e"}, "reunionRef": null, "voteRefs": null, "textesAssocies": {"texteAssocie": {"typeTexte": "BTA", "refTexteAssocie": "PIONSNR5S399BTA0006"}}}}}]}}, {"@xsi:type": "Etape_Type", "uid": "L16-AN1-46270", "codeActe": "AN1", "libelleActe": {"nomCanonique": "1\u00e8re lecture (2\u00e8me assembl\u00e9e saisie)", "libelleCourt": "1\u00e8re lecture"}, "organeRef": "PO791932", "dateActe": null, "actesLegislatifs": {"acteLegislatif": [{"@xsi:type": "DepotInitiativeNavette_Type", "uid": "L16-VD209625DIN", "codeActe": "AN1-DEPOT", "libelleActe": {"nomCanonique": "D\u00e9p\u00f4t d'une initiative en navette", "libelleCourt": "D\u00e9p\u00f4t d'une initiative en navette"}, "organeRef": "PO791932", "dateActe": "2022-10-20T00:00:00.000+02:00", "actesLegislatifs": null, "texteAssocie": "PIONANR5L16B0372", "provenance": "PO78718", "depotInitialLectureDefinitiveRef": null}, {"@xsi:type": "Etape_Type", "uid": "L16-AN1-COM-46270", "codeActe": "AN1-COM", "libelleActe": {"nomCanonique": "Travaux des commissions", "libelleCourt": "Travaux des commissions"}, "organeRef": "PO791932", "dateActe": null, "actesLegislatifs": {"acteLegislatif": {"@xsi:type": "Etape_Type", "uid": "L16-VD209626CF", "codeActe": "AN1-COM-FOND", "libelleActe": {"nomCanonique": "Travaux de la commission saisie au fond", "libelleCourt": "Travaux de la commission saisie au fond"}, "organeRef": "PO420120", "dateActe": null, "actesLegislatifs": {"acteLegislatif": [{"@xsi:type": "SaisieComFond_Type", "uid": "L16-VD209626CFS", "codeActe": "AN1-COM-FOND-SAISIE", "libelleActe": {"nomCanonique": "Renvoi en commission au fond", "libelleCourt": "Renvoi en commission au fond"}, "organeRef": "PO420120", "dateActe": "2022-10-20T00:00:00.000+02:00", "actesLegislatifs": null}, {"@xsi:type": "NominRapporteurs_Type", "uid": "L16-VD210698", "codeActe": "AN1-COM-FOND-NOMIN", "libelleActe": {"nomCanonique": "Nomination de rapporteur", "libelleCourt": "Nomination de rapporteur"}, "organeRef": "PO420120", "dateActe": "2022-12-14T00:00:00.000+01:00", "actesLegislatifs": null, "rapporteurs": {"rapporteur": [{"acteurRef": "PA793382", "typeRapporteur": "rapporteur"}, {"acteurRef": "PA720696", "typeRapporteur": "rapporteur"}]}, "reunion": null}, {"@xsi:type": "DiscussionCommission_Type", "uid": "L16-VD210526R31968", "codeActe": "AN1-COM-FOND-REUNION", "libelleActe": {"nomCanonique": "R\u00e9union de commission", "libelleCourt": "R\u00e9union de commission"}, "organeRef": "PO420120", "dateActe": "2022-12-14T09:30:00.000+01:00", "actesLegislatifs": null, "reunionRef": "RUANR5L16S2023IDC446328", "odjRef": "RUANR5L16S2023IDC446328PT31968"}, {"@xsi:type": "DiscussionCommission_Type", "uid": "L16-VD210526R31946", "codeActe": "AN1-COM-FOND-REUNION", "libelleActe": {"nomCanonique": "R\u00e9union de commission", "libelleCourt": "R\u00e9union de commission"}, "organeRef": "PO420120", "dateActe": "2022-12-14T15:00:00.000+01:00", "actesLegislatifs": null, "reunionRef": "RUANR5L16S2023IDC446329", "odjRef": "RUANR5L16S2023IDC446329PT31946"}, {"@xsi:type": "DiscussionCommission_Type", "uid": "L16-VD210526R32020", "codeActe": "AN1-COM-FOND-REUNION", "libelleActe": {"nomCanonique": "R\u00e9union de commission", "libelleCourt": "R\u00e9union de commission"}, "organeRef": "PO420120", "dateActe": "2023-01-16T15:45:00.000+01:00", "actesLegislatifs": null, "reunionRef": "RUANR5L16S2023IDC446550", "odjRef": "RUANR5L16S2023IDC446550PT32020"}, {"@xsi:type": "DepotRapport_Type", "uid": "L16-VD210715", "codeActe": "AN1-COM-FOND-RAPPORT", "libelleActe": {"nomCanonique": "D\u00e9p\u00f4t de rapport", "libelleCourt": "D\u00e9p\u00f4t de rapport"}, "organeRef": "PO420120", "dateActe": "2022-12-14T00:00:00.000+01:00", "actesLegislatifs": null, "texteAssocie": "RAPPANR5L16B0617", "texteAdopte": "PIONANR5L16BTC0617"}]}}}}, {"@xsi:type": "Etape_Type", "uid": "L16-AN1-DEBATS-46270", "codeActe": "AN1-DEBATS", "libelleActe": {"nomCanonique": "Discussion en s\u00e9ance publique", "libelleCourt": "Discussion en s\u00e9ance publique"}, "organeRef": "PO791932", "dateActe": null, "actesLegislatifs": {"acteLegislatif": [{"@xsi:type": "DiscussionSeancePublique_Type", "uid": "L16-VD210578S44987", "codeActe": "AN1-DEBATS-SEANCE", "libelleActe": {"nomCanonique": "Discussion en s\u00e9ance publique", "libelleCourt": "Discussion en s\u00e9ance publique"}, "organeRef": "PO791932", "dateActe": "2023-01-16T00:00:00.000+01:00", "actesLegislatifs": null, "reunionRef": "RUANR5L16S2023IDS26687", "odjRef": "RUANR5L16S2023IDS26687PT44987"}, {"@xsi:type": "Decision_Type", "uid": "L16-VD211081DEC", "codeActe": "AN1-DEBATS-DEC", "libelleActe": {"nomCanonique": "D\u00e9cision", "libelleCourt": "D\u00e9cision"}, "organeRef": "PO791932", "dateActe": "2023-01-16T00:00:00.000+01:00", "actesLegislatifs": null, "statutConclusion": {"fam_code": "TSORTF05", "libelle": "modifi\u00e9e"}, "reunionRef": "RUANR5L16S2023IDS26687", "voteRefs": {"voteRef": "VTANR5L16V837"}, "textesAssocies": {"texteAssocie": [{"typeTexte": "BTA", "refTexteAssocie": "PIONANR5L16BTA0058"}, {"typeTexte": "TAP", "refTexteAssocie": "PIONANR5L16TAP0058"}]}}]}}]}}, {"@xsi:type": "Etape_Type", "uid": "L16-SN2-46270", "codeActe": "SN2", "libelleActe": {"nomCanonique": "deuxi\u00e8me lecture", "libelleCourt": "2\u00e8me lecture"}, "organeRef": "PO78718", "dateActe": null, "actesLegislatifs": {"acteLegislatif": [{"@xsi:type": "DepotInitiativeNavette_Type", "uid": "L16-VD211090DIN", "codeActe": "SN2-DEPOT", "libelleActe": {"nomCanonique": "D\u00e9p\u00f4t d'une initiative en navette", "libelleCourt": "D\u00e9p\u00f4t d'une initiative en navette"}, "organeRef": "PO78718", "dateActe": "2023-01-17T00:00:00.000+01:00", "actesLegislatifs": null, "texteAssocie": "PIONSNR5S399B0244", "provenance": "PO791932", "depotInitialLectureDefinitiveRef": null}, {"@xsi:type": "Etape_Type", "uid": "L16-SN2-COM-46270", "codeActe": "SN2-COM", "libelleActe": {"nomCanonique": "Travaux des commissions", "libelleCourt": "Travaux des commissions"}, "organeRef": "PO78718", "dateActe": null, "actesLegislatifs": {"acteLegislatif": {"@xsi:type": "Etape_Type", "uid": "L16-VD211091CF", "codeActe": "SN2-COM-FOND", "libelleActe": {"nomCanonique": "Travaux de la commission saisie au fond", "libelleCourt": "Travaux de la commission saisie au fond"}, "organeRef": "PO211493", "dateActe": null, "actesLegislatifs": {"acteLegislatif": [{"@xsi:type": "SaisieComFond_Type", "uid": "L16-VD211091CFS", "codeActe": "SN2-COM-FOND-SAISIE", "libelleActe": {"nomCanonique": "Renvoi en commission au fond", "libelleCourt": "Renvoi en commission au fond"}, "organeRef": "PO211493", "dateActe": "2023-01-17T00:00:00.000+01:00", "actesLegislatifs": null}, {"@xsi:type": "DepotRapport_Type", "uid": "L16-VD211619", "codeActe": "SN2-COM-FOND-RAPPORT", "libelleActe": {"nomCanonique": "D\u00e9p\u00f4t de rapport", "libelleCourt": "D\u00e9p\u00f4t de rapport"}, "organeRef": "PO211493", "dateActe": "2023-02-08T00:00:00.000+01:00", "actesLegislatifs": null, "texteAssocie": "RAPPSNR5S399B0330", "texteAdopte": "PIONSNR5S399BTC0331"}]}}}}, {"@xsi:type": "Etape_Type", "uid": "L16-SN2-DEBATS-46270", "codeActe": "SN2-DEBATS", "libelleActe": {"nomCanonique": "Discussion en s\u00e9ance publique", "libelleCourt": "Discussion en s\u00e9ance publique"}, "organeRef": "PO78718", "dateActe": null, "actesLegislatifs": {"acteLegislatif": {"@xsi:type": "Decision_Type", "uid": "L16-VD211795DEC", "codeActe": "SN2-DEBATS-DEC", "libelleActe": {"nomCanonique": "D\u00e9cision", "libelleCourt": "D\u00e9cision"}, "organeRef": "PO78718", "dateActe": "2023-02-16T00:00:00.000+01:00", "actesLegislatifs": null, "statutConclusion": {"fam_code": "TSORTF02", "libelle": "adopt\u00e9e avec modifications"}, "reunionRef": null, "voteRefs": null, "textesAssocies": {"texteAssocie": {"typeTexte": "BTA", "refTexteAssocie": "PIONSNR5S399BTA0061"}}}}}]}}, {"@xsi:type": "Etape_Type", "uid": "L16-PROM-46270", "codeActe": "PROM", "libelleActe": {"nomCanonique": "Promulgation de la loi", "libelleCourt": "Promulgation de la loi"}, "organeRef": "PO717136", "dateActe": null, "actesLegislatifs": {"acteLegislatif": {"@xsi:type": "Promulgation_Type", "uid": "L16-VD211932PL", "codeActe": "PROM-PUB", "libelleActe": {"nomCanonique": "Promulgation d'une loi", "libelleCourt": "Promulgation d'une loi"}, "organeRef": "PO717136", "dateActe": "2023-02-28T00:00:00.000+01:00", "actesLegislatifs": null, "infoJO": {"typeJO": "JO_LOI_DECRET", "dateJO": "2023-03-01+01:00", "pageJO": null, "numJO": "51", "urlLegifrance": "http://www.legifrance.gouv.fr/WAspad/UnTexteDeJorf?numjo=PRMC2230275L", "referenceNOR": "PRMC2230275L"}, "urlEcheancierLoi": null, "codeLoi": "2023-140", "titreLoi": "cr\u00e9ant une aide universelle d'urgence pour les victimes de violences conjugales"}}}]}, "fusionDossier": null}}