{"dossierParlementaire": {"@xmlns": "http://schemas.assemblee-nationale.fr/referentiel", "@xmlns:xsi": "http://www.w3.org/2001/XMLSchema-instance", "@xsi:type": "DossierResolutionAN", "uid": "DLR5L16N49175", "legislature": "16", "titreDossier": {"titre": "Accentuer les efforts pour favoriser l\u2019acc\u00e8s de tous au logement", "titreChemin": "efforts_acces_de_tous_logement", "senatChemin": null}, "procedureParlementaire": {"code": "22", "libelle": "R\u00e9solution Article 34-1"}, "initiateur": {"acteurs": {"acteur": {"acteurRef": "PA720728", "mandatRef": "PM797157"}}}, "actesLegislatifs": {"acteLegislatif": {"@xsi:type": "Etape_Type", "uid": "L16-ANLUNI-49175", "codeActe": "ANLUNI", "libelleActe": {"nomCanonique": "Lecture unique"}, "organeRef": "PO791932", "dateActe": null, "actesLegislatifs": {"acteLegislatif": [{"@xsi:type": "DepotInitiative_Type", "uid": "L16-VD217255DI", "codeActe": "ANLUNI-DEPOT", "libelleActe": {"nomCanonique": "1er d\u00e9p\u00f4t d'une initiative.", "libelleCourt": "1er d\u00e9p\u00f4t d'une initiative."}, "organeRef": "PO791932", "dateActe": "2023-12-26T00:00:00.000+01:00", "actesLegislatifs": null, "texteAssocie": "PNREANR5L16B2046"}, {"@xsi:type": "Etape_Type", "uid": "L16-ANLUNI-DEBATS-49175", "codeActe": "ANLUNI-DEBATS", "libelleActe": {"nomCanonique": "Discussion en s\u00e9ance publique", "libelleCourt": "Discussion en s\u00e9ance publique"}, "organeRef": "PO791932", "dateActe": null, "actesLegislatifs": {"acteLegislatif": [{"@xsi:type": "DiscussionSeancePublique_Type", "uid": "L16-VD217353S47048", "codeActe": "ANLUNI-DEBATS-SEANCE", "libelleActe": {"nomCanonique": "Discussion en s\u00e9ance publique", "libelleCourt": "Discussion en s\u00e9ance publique"}, "organeRef": "PO791932", "dateActe": "2024-01-18T00:00:00.000+01:00", "actesLegislatifs": null, "reunionRef": "RUANR5L16S2024IDS28004", "odjRef": "RUANR5L16S2024IDS28004PT47048"}, {"@xsi:type": "DiscussionSeancePublique_Type", "uid": "L16-VD217353S47054", "codeActe": "ANLUNI-DEBATS-SEANCE", "libelleActe": {"nomCanonique": "Discussion en s\u00e9ance publique", "libelleCourt": "Discussion en s\u00e9ance publique"}, "organeRef": "PO791932", "dateActe": "2024-01-18T00:00:00.000+01:00", "actesLegislatifs": null, "reunionRef": "RUANR5L16S2024IDS28005", "odjRef": "RUANR5L16S2024IDS28005PT47054"}, {"@xsi:type": "Decision_Type", "uid": "L16-VD217460DEC", "codeActe": "ANLUNI-DEBATS-DEC", "libelleActe": {"nomCanonique": "D\u00e9cision", "libelleCourt": "D\u00e9cision"}, "organeRef": "PO791932", "dateActe": "2024-01-18T00:00:00.000+01:00", "actesLegislatifs": null, "statutConclusion": {"fam_code": "TSORTF01", "libelle": "adopt\u00e9e"}, "reunionRef": "RUANR5L16S2024IDS28005", "voteRefs": {"voteRef": "VTANR5L16V3219"}, "textesAssocies": {"texteAssocie": {"typeTexte": "BTA", "refTexteAssocie": "RIONANR5L16BTA0227"}}}]}}]}}}, "fusionDossier": null}}