{"dossierParlementaire": {"@xmlns": "http://schemas.assemblee-nationale.fr/referentiel", "@xmlns:xsi": "http://www.w3.org/2001/XMLSchema-instance", "@xsi:type": "DossierLegislatif_Type", "uid": "DLR5L16N46739", "legislature": "16", "titreDossier": {"titre": "R\u00e9tablir l\u2019implantation locale des parlementaires", "titreChemin": "retablir_implantation_locale_parlementaires", "senatChemin": null}, "procedureParlementaire": {"code": "5", "libelle": "Projet ou proposition de loi organique"}, "initiateur": {"acteurs": {"acteur": {"acteurRef": "PA720822", "mandatRef": "PM797058"}}}, "actesLegislatifs": {"acteLegislatif": {"@xsi:type": "Etape_Type", "uid": "L16-AN1-46739", "codeActe": "AN1", "libelleActe": {"nomCanonique": "1\u00e8re lecture (1\u00e8re assembl\u00e9e saisie)", "libelleCourt": "1\u00e8re lecture"}, "organeRef": "PO791932", "dateActe": null, "actesLegislatifs": {"acteLegislatif": [{"@xsi:type": "DepotInitiative_Type", "uid": "L16-VD210321DI", "codeActe": "AN1-DEPOT", "libelleActe": {"nomCanonique": "1er d\u00e9p\u00f4t d'une initiative.", "libelleCourt": "1er d\u00e9p\u00f4t d'une initiative."}, "organeRef": "PO791932", "dateActe": "2022-11-24T00:00:00.000+01:00", "actesLegislatifs": null, "texteAssocie": "PIONANR5L16B0519"}, {"@xsi:type": "Etape_Type", "uid": "L16-AN1-COM-46739", "codeActe": "AN1-COM", "libelleActe": {"nomCanonique": "Travaux des commissions", "libelleCourt": "Travaux des commissions"}, "organeRef": "PO791932", "dateActe": null, "actesLegislatifs": {"acteLegislatif": {"@xsi:type": "Etape_Type", "uid": "L16-VD210322CF", "codeActe": "AN1-COM-FOND", "libelleActe": {"nomCanonique": "Travaux de la commission saisie au fond", "libelleCourt": "Travaux de la commission saisie au fond"}, "organeRef": "PO59051", "dateActe": null, "actesLegislatifs": {"acteLegislatif": {"@xsi:type": "SaisieComFond_Type", "uid": "L16-VD210322CFS", "codeActe": "AN1-COM-FOND-SAISIE", "libelleActe": {"nomCanonique": "Renvoi en commission au fond", "libelleCourt": "Renvoi en commission au fond"}, "organeRef": "PO59051", "dateActe": "2022-11-24T00:00:00.000+01:00", "actesLegislatifs": null}}}}}, {"@xsi:type": "RetraitInitiative_Type", "uid": "L16-VD210350", "codeActe": "AN1-RTRINI", "libelleActe": {"nomCanonique": "Retrait d'une initiative", "libelleCourt": "Retrait d'une initiative"}, "organeRef": "PO791932", "dateActe": "2022-11-28T00:00:00.000+01:00", "actesLegislatifs": null, "texteAssocie": "PIONANR5L16B0519"}]}}}, "fusionDossier": null}}