{"dossierParlementaire": {"@xmlns": "http://schemas.assemblee-nationale.fr/referentiel", "@xmlns:xsi": "http://www.w3.org/2001/XMLSchema-instance", "@xsi:type": "DossierLegislatif_Type", "uid": "DLR5L16N49458", "legislature": "16", "titreDossier": {"titre": "Reconna\u00eetre et prot\u00e9ger la sant\u00e9 menstruelle et gyn\u00e9cologique dans le monde du travail", "titreChemin": "reconnaitre_sante_menstruelle_gynecologique_travail", "senatChemin": null}, "procedureParlementaire": {"code": "2", "libelle": "Proposition de loi ordinaire"}, "initiateur": {"acteurs": {"acteur": {"acteurRef": "PA793708", "mandatRef": "PM796488"}}}, "actesLegislatifs": {"acteLegislatif": {"@xsi:type": "Etape_Type", "uid": "L16-AN1-49458", "codeActe": "AN1", "libelleActe": {"nomCanonique": "1\u00e8re lecture (1\u00e8re assembl\u00e9e saisie)", "libelleCourt": "1\u00e8re lecture"}, "organeRef": "PO791932", "dateActe": null, "actesLegislatifs": {"acteLegislatif": [{"@xsi:type": "DepotInitiative_Type", "uid": "L16-VD218068DI", "codeActe": "AN1-DEPOT", "libelleActe": {"nomCanonique": "1er d\u00e9p\u00f4t d'une initiative.", "libelleCourt": "1er d\u00e9p\u00f4t d'une initiative."}, "organeRef": "PO791932", "dateActe": "2024-02-20T00:00:00.000+01:00", "actesLegislatifs": null, "texteAssocie": "PIONANR5L16B2227"}, {"@xsi:type": "Etape_Type", "uid": "L16-AN1-COM-49458", "codeActe": "AN1-COM", "libelleActe": {"nomCanonique": "Travaux des commissions", "libelleCourt": "Travaux des commissions"}, "organeRef": "PO791932", "dateActe": null, "actesLegislatifs": {"acteLegislatif": {"@xsi:type": "Etape_Type", "uid": "L16-VD218070CF", "codeActe": "AN1-COM-FOND", "libelleActe": {"nomCanonique": "Travaux de la commission saisie au fond", "libelleCourt": "Travaux de la commission saisie au fond"}, "organeRef": "PO420120", "dateActe": null, "actesLegislatifs": {"acteLegislatif": [{"@xsi:type": "SaisieComFond_Type", "uid": "L16-VD218070CFS", "codeActe": "AN1-COM-FOND-SAISIE", "libelleActe": {"nomCanonique": "Renvoi en commission au fond", "libelleCourt": "Renvoi en commission au fond"}, "organeRef": "PO420120", "dateActe": "2024-02-20T00:00:00.000+01:00", "actesLegislatifs": null}, {"@xsi:type": "NominRapporteurs_Type", "uid": "L16-VD218463", "codeActe": "AN1-COM-FOND-NOMIN", "libelleActe": {"nomCanonique": "Nomination de rapporteur", "libelleCourt": "Nomination de rapporteur"}, "organeRef": "PO420120", "dateActe": "2024-03-13T00:00:00.000+01:00", "actesLegislatifs": null, "rapporteurs": {"rapporteur": {"acteurRef": "PA793708", "typeRapporteur": "rapporteur"}}, "reunion": null}, {"@xsi:type": "DiscussionCommission_Type", "uid": "L16-VD218546R33956", "codeActe": "AN1-COM-FOND-REUNION", "libelleActe": {"nomCanonique": "R\u00e9union de commission", "libelleCourt": "R\u00e9union de commission"}, "organeRef": "PO420120", "dateActe": "2024-03-13T09:55:00.000+01:00", "actesLegislatifs": null, "reunionRef": "RUANR5L16S2024IDC451866", "odjRef": "RUANR5L16S2024IDC451866PT33956"}, {"@xsi:type": "DiscussionCommission_Type", "uid": "L16-VD218546R33913", "codeActe": "AN1-COM-FOND-REUNION", "libelleActe": {"nomCanonique": "R\u00e9union de commission", "libelleCourt": "R\u00e9union de commission"}, "organeRef": "PO420120", "dateActe": "2024-03-27T09:30:00.000+01:00", "actesLegislatifs": null, "reunionRef": "RUANR5L16S2024IDC452078", "odjRef": "RUANR5L16S2024IDC452078PT33913"}, {"@xsi:type": "DepotRapport_Type", "uid": "L16-VD218799", "codeActe": "AN1-COM-FOND-RAPPORT", "libelleActe": {"nomCanonique": "D\u00e9p\u00f4t de rapport", "libelleCourt": "D\u00e9p\u00f4t de rapport"}, "organeRef": "PO420120", "dateActe": "2024-03-27T00:00:00.000+01:00", "actesLegislatifs": null, "texteAssocie": "RAPPANR5L16B2406", "texteAdopte": "PIONANR5L16BTC2406"}]}}}}]}}}, "fusionDossier": null}}