{"document": {"@xmlns": "http://schemas.assemblee-nationale.fr/referentiel", "@xmlns:xsi": "http://www.w3.org/2001/XMLSchema-instance", "@xsi:type": "texteLoi_Type", "uid": "PIONSNR5S419B0070", "legislature": null, "cycleDeVie": {"chrono": {"dateCreation": "2023-10-27T00:00:00.000+02:00", "dateDepot": "2023-10-26T00:00:00.000+02:00", "datePublication": null, "datePublicationWeb": null}}, "denominationStructurelle": "Proposition de loi", "provenance": "Texte D\u00e9pos\u00e9", "titres": {"titrePrincipal": "proposition de loi de programmation polaire pour les ann\u00e9es 2024 \u00e0 2030", "titrePrincipalCourt": "de programmation polaire pour les ann\u00e9es 2024 \u00e0 2030"}, "divisions": null, "dossierRef": "DLR5L16N48820", "redacteur": null, "classification": {"famille": {"depot": {"code": "INITDEP", "libelle": "Initiative en 1er D\u00e9p\u00f4t"}, "classe": {"code": "PIONLOI", "libelle": "Proposition de loi"}}, "type": {"code": "PION", "libelle": "Proposition de loi"}, "sousType": null, "statutAdoption": null}, "auteurs": {"auteur": [{"acteur": {"acteurRef": "PA719408", "qualite": "auteur"}}, {"acteur": {"acteurRef": "PA415454", "qualite": "auteur"}}, {"acteur": {"acteurRef": "PA2337", "qualite": "auteur"}}, {"acteur": {"acteurRef": "PA827902", "qualite": "auteur"}}, {"acteur": {"acteurRef": "PA760322", "qualite": "auteur"}}, {"acteur": {"acteurRef": "PA827916", "qualite": "auteur"}}, {"acteur": {"acteurRef": "PA721166", "qualite": "auteur"}}, {"acteur": {"acteurRef": "PA703506", "qualite": "auteur"}}, {"acteur": {"acteurRef": "PA267387", "qualite": "auteur"}}, {"acteur": {"acteurRef": "PA775234", "qualite": "auteur"}}, {"acteur": {"acteurRef": "PA736233", "qualite": "auteur"}}, {"acteur": {"acteurRef": "PA775244", "qualite": "auteur"}}, {"acteur": {"acteurRef": "PA703535", "qualite": "auteur"}}, {"acteur": {"acteurRef": "PA736165", "qualite": "auteur"}}, {"acteur": {"acteurRef": "PA429840", "qualite": "auteur"}}, {"acteur": {"acteurRef": "PA827972", "qualite": "auteur"}}, {"acteur": {"acteurRef": "PA827980", "qualite": "auteur"}}, {"acteur": {"acteurRef": "PA415499", "qualite": "auteur"}}, {"acteur": {"acteurRef": "PA775266", "qualite": "auteur"}}, {"acteur": {"acteurRef": "PA736208", "qualite": "auteur"}}, {"acteur": {"acteurRef": "PA775278", "qualite": "auteur"}}, {"acteur": {"acteurRef": "PA303995", "qualite": "auteur"}}, {"acteur": {"acteurRef": "PA736179", "qualite": "auteur"}}, {"acteur": {"acteurRef": "PA703514", "qualite": "auteur"}}, {"acteur": {"acteurRef": "PA703537", "qualite": "auteur"}}]}, "organesReferents": {"organeRef": "PO211490"}, "correction": null, "notice": {"numNotice": "70", "formule": "de programmation polaire pour les ann\u00e9es 2024 \u00e0 2030", "adoptionConforme": "false"}, "indexation": null, "imprimerie": {"ISSN": null, "ISBN": null, "DIAN": null, "nbPage": null, "prix": null}, "coSignataires": null, "depotAmendements": {"amendementsSeance": {"amendable": "false", "dateLimiteDepot": null}}}}